genja/__init__.py
genja/builder.py
genja/main.py
genja/server.py
genja/static/__init__.py
genja/static/about.md
genja/static/apple.jpg
genja/static/apple.md
genja/static/broccoli.md
genja/static/contact.md
genja/static/genja.toml
genja/static/index.html
genja/static/orange.md
genja/static/page.html
genja/static/post.html
genja/static/spinach.md
genja/static/styles.css
genja-25.10.dist-info/METADATA
genja-25.10.dist-info/WHEEL
genja-25.10.dist-info/entry_points.txt
genja-25.10.dist-info/licenses/LICENSE.md
genja-25.10.dist-info/RECORD
