Metadata-Version: 2.4
Name: genja
Version: 25.10
Summary: Static website generator
Project-URL: Documentation, https://genja.readthedocs.io
Project-URL: GitHub, https://github.com/wigging/genja
Author: Gavin Wiggins
License-Expression: MIT
License-File: LICENSE.md
Classifier: License :: OSI Approved :: MIT License
Classifier: Operating System :: OS Independent
Classifier: Programming Language :: Python :: 3
Requires-Python: >=3.13
Requires-Dist: beautifulsoup4>=4.13.3
Requires-Dist: jinja2>=3.1.5
Requires-Dist: livereload>=2.7.1
Requires-Dist: markdown>=3.7
Provides-Extra: docs
Requires-Dist: furo>=2024.8.6; extra == 'docs'
Requires-Dist: myst-parser>=4.0.1; extra == 'docs'
Requires-Dist: sphinx>=8.2.1; extra == 'docs'
